date_time_event/__init__.py
date_time_event/utils.py
test/__init__.py
test/test_event.py
date_time_event-0.0.1.dist-info/LICENSE
date_time_event-0.0.1.dist-info/METADATA
date_time_event-0.0.1.dist-info/WHEEL
date_time_event-0.0.1.dist-info/top_level.txt
date_time_event-0.0.1.dist-info/RECORD
