Metadata-Version: 2.1
Name: date-time-event
Version: 0.0.1
Summary: A very simple package to trigger events at a specific DateTime.
Home-page: https://github.com/Saadmairaj/date-time-event/
Author: Saad Mairaj
Author-email: Saadmairaj@yahoo.in
License: MIT
Project-URL: Bug Reports, https://github.com/Saadmairaj/date-time-event/issues
Project-URL: Source, https://github.com/Saadmairaj/date-time-event
Keywords: python,python3,threading,datetime-format,date-event,time-event
Platform: UNKNOWN
Classifier: Development Status :: 6 - Mature
Classifier: Intended Audience :: Developers
Classifier: Intended Audience :: Education
Classifier: Intended Audience :: End Users/Desktop
Classifier: Operating System :: OS Independent
Classifier: Programming Language :: Python :: 3 :: Only
Classifier: Programming Language :: Python :: 3.0
Classifier: Programming Language :: Python :: 3.1
Classifier: Programming Language :: Python :: 3.2
Classifier: Programming Language :: Python :: 3.3
Classifier: Programming Language :: Python :: 3.4
Classifier: Programming Language :: Python :: 3.5
Classifier: Programming Language :: Python :: 3.6
Classifier: Programming Language :: Python :: 3.7
Classifier: Programming Language :: Python :: 3.8
Classifier: Programming Language :: Python :: 3.9
Classifier: Topic :: Software Development
Classifier: Topic :: Software Development :: Build Tools
Classifier: Topic :: Software Development :: Libraries :: Python Modules
Requires-Python: >=3
